{"title":"alookso ─ 둘러보기 ─ 최신 글","url":"https://alook.so/discover/latest","favicon":"https://alook.so/assets/favicon/favicon-32x32-8fc0ef8efcf005e31acc7291922e138cf3d3654531e4556566ca5cc4797a6793.png","elements":[{"title":"외부불경제로 비용을 강제하는 것은 안될까요?","contents":"<a class=\"text-lg text-gray-800 font-semibold line-clamp-2\" href=\"/posts/1RtmxY\">외부불경제로 비용을 강제하는 것은 안될까요?</a>","link":"https://alook.so/posts/1RtmxY","retrieved":1646734421256},{"title":"고통속에 열매를 맺다","contents":"<a class=\"text-lg text-gray-800 font-semibold line-clamp-2\" href=\"/posts/Yyt7kD\">고통속에 열매를 맺다</a>","link":"https://alook.so/posts/Yyt7kD","retrieved":1646734421259},{"title":"어느날 공황발작이 왔다.","contents":"<a class=\"text-lg text-gray-800 font-semibold line-clamp-2\" href=\"/posts/bWtx1y\">어느날 공황발작이 왔다.</a>","link":"https://alook.so/posts/bWtx1y","retrieved":1646734421259},{"title":"독서 후 끄적끄적","contents":"<a class=\"text-lg text-gray-800 font-semibold line-clamp-2\" href=\"/posts/a0tVEe\">독서 후 끄적끄적</a>","link":"https://alook.so/posts/a0tVEe","retrieved":1646734421259}]}